penpot_mcp/__init__.py
penpot_mcp/api/__init__.py
penpot_mcp/api/penpot_api.py
penpot_mcp/resources/penpot-schema.json
penpot_mcp/resources/penpot-tree-schema.json
penpot_mcp/server/__init__.py
penpot_mcp/server/client.py
penpot_mcp/server/mcp_server.py
penpot_mcp/tools/__init__.py
penpot_mcp/tools/penpot_tree.py
penpot_mcp/tools/cli/__init__.py
penpot_mcp/tools/cli/tree_cmd.py
penpot_mcp/tools/cli/validate_cmd.py
penpot_mcp/utils/__init__.py
penpot_mcp/utils/cache.py
penpot_mcp/utils/config.py
penpot_mcp/utils/http_server.py
penpot_mcp-0.1.2.dist-info/METADATA
penpot_mcp-0.1.2.dist-info/WHEEL
penpot_mcp-0.1.2.dist-info/entry_points.txt
penpot_mcp-0.1.2.dist-info/top_level.txt
penpot_mcp-0.1.2.dist-info/RECORD
