Metadata-Version: 2.4
Name: penpot-mcp
Version: 0.1.2
Summary: Model Context Protocol server for Penpot - AI-powered design workflow automation
Author-email: Montevive AI Team <info@montevive.ai>
License-Expression: MIT
Project-URL: Homepage, https://github.com/montevive/penpot-mcp
Project-URL: Repository, https://github.com/montevive/penpot-mcp.git
Project-URL: Issues, https://github.com/montevive/penpot-mcp/issues
Project-URL: Documentation, https://github.com/montevive/penpot-mcp#readme
Project-URL: Changelog, https://github.com/montevive/penpot-mcp/releases
Keywords: penpot,mcp,llm,ai,design,prototyping,claude,cursor,model-context-protocol
Classifier: Development Status :: 4 - Beta
Classifier: Intended Audience :: Developers
Classifier: Intended Audience :: End Users/Desktop
Classifier: Programming Language :: Python :: 3
Classifier: Programming Language :: Python :: 3.10
Classifier: Programming Language :: Python :: 3.11
Classifier: Programming Language :: Python :: 3.12
Classifier: Programming Language :: Python :: 3.13
Classifier: Topic :: Software Development :: Libraries :: Python Modules
Classifier: Topic :: Multimedia :: Graphics :: Graphics Conversion
Classifier: Topic :: Scientific/Engineering :: Artificial Intelligence
Classifier: Topic :: Software Development :: User Interfaces
Classifier: Environment :: Console
Classifier: Operating System :: OS Independent
Requires-Python: >=3.10
Requires-Dist: mcp>=1.7.0
Requires-Dist: python-dotenv>=1.0.0
Requires-Dist: requests>=2.26.0
Requires-Dist: gunicorn>=20.1.0
Requires-Dist: anytree>=2.8.0
Requires-Dist: jsonschema>=4.0.0
Requires-Dist: PyYAML>=6.0.0
Requires-Dist: twine>=6.1.0
Provides-Extra: dev
Requires-Dist: pytest>=7.4.0; extra == "dev"
Requires-Dist: pytest-mock>=3.11.1; extra == "dev"
Requires-Dist: pytest-cov>=4.1.0; extra == "dev"
Requires-Dist: flake8>=6.1.0; extra == "dev"
Requires-Dist: flake8-docstrings>=1.7.0; extra == "dev"
Requires-Dist: pre-commit>=3.5.0; extra == "dev"
Requires-Dist: isort>=5.12.0; extra == "dev"
Requires-Dist: autopep8>=2.0.4; extra == "dev"
Requires-Dist: pyupgrade>=3.13.0; extra == "dev"
Requires-Dist: setuptools>=65.5.0; extra == "dev"
Provides-Extra: cli
Requires-Dist: mcp[cli]>=1.7.0; extra == "cli"
